multiplicity/__init__.py
multiplicity/torch.py
multiplicity-2.1.0.dist-info/LICENSE
multiplicity-2.1.0.dist-info/METADATA
multiplicity-2.1.0.dist-info/WHEEL
multiplicity-2.1.0.dist-info/RECORD
