Metadata-Version: 2.1
Name: multiplicity
Version: 2.1.0
Summary: Predictive multiplicity for deep learning
License: MIT
Author: Bogdan Kulynych
Author-email: bogdan@kulyny.ch
Requires-Python: >=3.10,<4.0
Classifier: License :: OSI Approved :: MIT License
Classifier: Programming Language :: Python :: 3
Classifier: Programming Language :: Python :: 3.10
Classifier: Programming Language :: Python :: 3.11
Classifier: Programming Language :: Python :: 3.12
Requires-Dist: torch (>=2.0.0)
Requires-Dist: tqdm (>=4.66.1,<5.0.0)
